Metadata-Version: 1.1
Name: capidup-cli
Version: 1.0.0
Summary: Quickly find duplicate files in directories (CLI utility)
Home-page: https://github.com/israel-lugo/capidup-cli
Author: Israel G. Lugo
Author-email: israel.lugo@lugosys.com
License: GPLv3+
Platform: UNKNOWN
Classifier: Development Status :: 5 - Production/Stable
Classifier: Intended Audience :: End Users/Desktop
Classifier: License :: OSI Approved :: GNU General Public License v3 or later (GPLv3+)
Classifier: Programming Language :: Python :: 2
Classifier: Programming Language :: Python :: 2.6
Classifier: Programming Language :: Python :: 2.7
Classifier: Programming Language :: Python :: 3
Classifier: Programming Language :: Python :: 3.2
Classifier: Programming Language :: Python :: 3.3
Classifier: Programming Language :: Python :: 3.4
Classifier: Programming Language :: Python :: 3.5
Classifier: Topic :: System :: Filesystems
Classifier: Topic :: Utilities
